D4CMPP/__init__.py
D4CMPP/_main.py
D4CMPP/grid_search.py
D4CMPP/network_refer.yaml
D4CMPP/_Data/Aqsoldb.csv
D4CMPP/_Data/BradleyMP.csv
D4CMPP/_Data/Lipophilicity.csv
D4CMPP/_Data/__init__.py
D4CMPP/_Data/optical.csv
D4CMPP/_Data/test.csv
D4CMPP/networks/AFP_model.py
D4CMPP/networks/AFPwithSolv_model.py
D4CMPP/networks/AGC_model.py
D4CMPP/networks/ALIGNN_model.py
D4CMPP/networks/ALIGNNwithSolv_model.py
D4CMPP/networks/DMPNN_model.py
D4CMPP/networks/DMPNNwithSolv_model.py
D4CMPP/networks/GAT_model.py
D4CMPP/networks/GATwithSolv_model.py
D4CMPP/networks/GCN_model.py
D4CMPP/networks/GCNwithSolv_model.py
D4CMPP/networks/GC_model.py
D4CMPP/networks/ISATPM_model.py
D4CMPP/networks/ISAT_model.py
D4CMPP/networks/MPNN_model.py
D4CMPP/networks/MPNNwithSolv_model.py
D4CMPP/networks/MegNet_model.py
D4CMPP/networks/MegNetwithSolv_model.py
D4CMPP/networks/.ipynb_checkpoints/GCN_model-checkpoint.py
D4CMPP/networks/src/AFP.py
D4CMPP/networks/src/AGC.py
D4CMPP/networks/src/ALIGNN.py
D4CMPP/networks/src/BiDropout.py
D4CMPP/networks/src/DMPNN.py
D4CMPP/networks/src/GAT.py
D4CMPP/networks/src/GC.py
D4CMPP/networks/src/GCN.py
D4CMPP/networks/src/ISAT.py
D4CMPP/networks/src/Linear.py
D4CMPP/networks/src/MPNN.py
D4CMPP/networks/src/MegNet.py
D4CMPP/networks/src/SolventLayer.py
D4CMPP/networks/src/distGCN.py
D4CMPP/src/PostProcessor.py
D4CMPP/src/__init__.py
D4CMPP/src/Analyzer/ISAAnalyzer.py
D4CMPP/src/Analyzer/ISAwSAnalyzer.py
D4CMPP/src/Analyzer/MolAnalyzer.py
D4CMPP/src/Analyzer/__init__.py
D4CMPP/src/Analyzer/_analyzer.py
D4CMPP/src/DataManager/ISADataManager.py
D4CMPP/src/DataManager/ISADataManager_withSolv.py
D4CMPP/src/DataManager/MolDataManager.py
D4CMPP/src/DataManager/OverallDataManager.py
D4CMPP/src/DataManager/TripletDataManager.py
D4CMPP/src/DataManager/__init__.py
D4CMPP/src/DataManager/Dataset/GraphDataset.py
D4CMPP/src/DataManager/Dataset/ISAGraphDataset.py
D4CMPP/src/DataManager/Dataset/ISAGraphDataset_withSolv.py
D4CMPP/src/DataManager/Dataset/OverallGraphDataset.py
D4CMPP-1.242.dist-info/LICENSE
D4CMPP-1.242.dist-info/METADATA
D4CMPP-1.242.dist-info/WHEEL
D4CMPP-1.242.dist-info/top_level.txt
D4CMPP-1.242.dist-info/RECORD
