Metadata-Version: 2.1
Name: D4CMPP
Version: 1.242
Summary: Molecular property prediction based on Graph Convolution Network published by Deep4Chem
Home-page: https://github.com/phillip1998/D4C_MPP
Author: Park Jinyong
Author-email: phillip1998@korea.ac.kr
Classifier: Programming Language :: Python :: 3
Classifier: License :: OSI Approved :: MIT License
Classifier: Operating System :: OS Independent
Requires-Python: >=3.8
License-File: LICENSE
Requires-Dist: torch (>=2)
Requires-Dist: dgl (>=1)
Requires-Dist: tqdm
Requires-Dist: pandas
Requires-Dist: numpy
Requires-Dist: matplotlib
Requires-Dist: pyyaml
Requires-Dist: rdkit
Requires-Dist: scikit-learn
Requires-Dist: prettytable
